utils4DD/EmailSmtp_V1_1.py
utils4DD/__init__.py
utils4DD/configFiles.py
utils4DD/mplExtended.py
utils4DD/utils.py
utils4DD/conf/colormaps.pkl
utils4DD/conf/units.csv
utils4DD/confFilesScreeningBuilding/calculatedVars.csv
utils4DD/confFilesScreeningBuilding/compteurs.csv
utils4DD/confFilesScreeningBuilding/configurationMeteo.csv
utils4DD/confFilesScreeningBuilding/predefinedCategories.csv
utils4DD/confFilesScreeningBuilding/screenBuilding-10001-001-ConfigurationPLC.csv
utils4DD/confFilesScreeningBuilding/variables.csv
utils4DD/confFilesSmallPowerDash/20210526_Veyrat_Interfaces_Endymion_Alpha.pdf
utils4DD/confFilesSmallPowerDash/SmallPower-10002-001-ConfigurationPLC.csv
utils4DD/confFilesSmallPowerDash/listTagsEAUprocess.txt
utils4DD/confFilesSmallPowerDash/powerGroups.csv
utils4DD/confFilesSmallPowerDash/predefinedCategories.csv
utils4DD/confFilesSmallPowerDash/spark.conf
utils4DD/confFilesSmallPowerDash/tagLegend.csv
utils4DD/confFilesSmallPowerDash/typeGraph.csv
utils4DD-1.9.2.dist-info/METADATA
utils4DD-1.9.2.dist-info/WHEEL
utils4DD-1.9.2.dist-info/top_level.txt
utils4DD-1.9.2.dist-info/RECORD
